imbalanced_ensemble/__init__.py
imbalanced_ensemble/_version.py
imbalanced_ensemble/base.py
imbalanced_ensemble/exceptions.py
imbalanced_ensemble/pipeline.py
imbalanced_ensemble/datasets/__init__.py
imbalanced_ensemble/datasets/_imbalance.py
imbalanced_ensemble/datasets/_zenodo.py
imbalanced_ensemble/datasets/tests/__init__.py
imbalanced_ensemble/datasets/tests/test_imbalance.py
imbalanced_ensemble/datasets/tests/test_zenodo.py
imbalanced_ensemble/ensemble/__init__.py
imbalanced_ensemble/ensemble/_bagging.py
imbalanced_ensemble/ensemble/_boost.py
imbalanced_ensemble/ensemble/base.py
imbalanced_ensemble/ensemble/compatible/__init__.py
imbalanced_ensemble/ensemble/compatible/adaboost_compatible.py
imbalanced_ensemble/ensemble/compatible/bagging_compatible.py
imbalanced_ensemble/ensemble/over_sampling/__init__.py
imbalanced_ensemble/ensemble/over_sampling/kmeans_smote_boost.py
imbalanced_ensemble/ensemble/over_sampling/over_bagging.py
imbalanced_ensemble/ensemble/over_sampling/over_boost.py
imbalanced_ensemble/ensemble/over_sampling/smote_bagging.py
imbalanced_ensemble/ensemble/over_sampling/smote_boost.py
imbalanced_ensemble/ensemble/reweighting/__init__.py
imbalanced_ensemble/ensemble/reweighting/adacost.py
imbalanced_ensemble/ensemble/reweighting/adauboost.py
imbalanced_ensemble/ensemble/reweighting/asymmetric_boost.py
imbalanced_ensemble/ensemble/under_sampling/__init__.py
imbalanced_ensemble/ensemble/under_sampling/balance_cascade.py
imbalanced_ensemble/ensemble/under_sampling/balanced_random_forest.py
imbalanced_ensemble/ensemble/under_sampling/easy_ensemble.py
imbalanced_ensemble/ensemble/under_sampling/rus_boost.py
imbalanced_ensemble/ensemble/under_sampling/self_paced_ensemble.py
imbalanced_ensemble/ensemble/under_sampling/under_bagging.py
imbalanced_ensemble/metrics/__init__.py
imbalanced_ensemble/metrics/_classification.py
imbalanced_ensemble/metrics/pairwise.py
imbalanced_ensemble/metrics/tests/__init__.py
imbalanced_ensemble-0.2.3.dist-info/LICENSE
imbalanced_ensemble-0.2.3.dist-info/METADATA
imbalanced_ensemble-0.2.3.dist-info/WHEEL
imbalanced_ensemble-0.2.3.dist-info/top_level.txt
imbalanced_ensemble-0.2.3.dist-info/RECORD
