Metadata-Version: 2.1
Name: imbalanced-ensemble
Version: 0.2.3
Summary: Toolbox for ensemble learning on class-imbalanced dataset.
Home-page: https://github.com/ZhiningLiu1998/imbalanced-ensemble
Author: Zhining Liu
Author-email: zhining.liu@outlook.com
Maintainer: Zhining Liu
Maintainer-email: zhining.liu@outlook.com
License: MIT
Project-URL: Documentation, https://imbalanced-ensemble.readthedocs.io/
Project-URL: Source, https://github.com/ZhiningLiu1998/imbalanced-ensemble
Project-URL: Tracker, https://github.com/ZhiningLiu1998/imbalanced-ensemble/issues
Project-URL: Changelog, https://imbalanced-ensemble.readthedocs.io/en/latest/release_history.html
Project-URL: Download, https://pypi.org/project/imbalanced-ensemble/#files
Classifier: Intended Audience :: Science/Research
Classifier: Intended Audience :: Developers
Classifier: License :: OSI Approved :: MIT License
Classifier: Programming Language :: C
Classifier: Programming Language :: Python
Classifier: Topic :: Software Development
Classifier: Topic :: Scientific/Engineering
Classifier: Operating System :: Microsoft :: Windows
Classifier: Operating System :: POSIX
Classifier: Operating System :: Unix
Classifier: Operating System :: MacOS
Classifier: Programming Language :: Python :: 3.9
Classifier: Programming Language :: Python :: 3.10
Classifier: Programming Language :: Python :: 3.11
Classifier: Programming Language :: Python :: 3 :: Only
Provides-Extra: dev
Provides-Extra: test
Provides-Extra: doc
License-File: LICENSE
